ip_enrich.py
ip_enrich-0.1.0.dist-info/WHEEL
ip_enrich-0.1.0.dist-info/METADATA
ip_enrich-0.1.0.dist-info/RECORD
