Metadata-Version: 2.1
Name: ip-enrich
Version: 0.1.0
Summary: Enrich IP addresses with metadata and threat intelligence indicators.
License: GPLv3
Author: Sebastian Garcia
Author-email: eldraco@gmail.com
Requires-Python: >=3.8,<4.0
Classifier: License :: Other/Proprietary License
Classifier: Programming Language :: Python :: 3
Classifier: Programming Language :: Python :: 3.10
Classifier: Programming Language :: Python :: 3.8
Classifier: Programming Language :: Python :: 3.9
Requires-Dist: requests (>=2.27.1,<3.0.0)
Requires-Dist: shodan (>=1.26.1,<2.0.0)
